ws_storage/__init__.py
ws_storage/client.py
ws_storage/coro_queue.py
ws_storage/daemon.py
ws_storage/packet.py
ws_storage/protocol.py
ws_storage/server.py
ws_storage/filesystem/__init__.py
ws_storage/tests/__init__.py
ws_storage/tests/client.py
ws_storage-0.5.1.data/scripts/ws_storage
ws_storage-0.5.1.dist-info/DESCRIPTION.rst
ws_storage-0.5.1.dist-info/METADATA
ws_storage-0.5.1.dist-info/RECORD
ws_storage-0.5.1.dist-info/WHEEL
ws_storage-0.5.1.dist-info/metadata.json
ws_storage-0.5.1.dist-info/top_level.txt
