Metadata-Version: 2.0
Name: ws-storage
Version: 0.5.1
Summary: pytohn object storage
Home-page: http://github.com/chuck1/ws_storage
Author: Charles Rymal
Author-email: charlesrymal@gmail.com
License: MIT
Platform: UNKNOWN
